LICENSE
README.md
examples.ipynb
psychedelic.png
setup.py
psychedelic/__init__.py
psychedelic/jupyter_implicit.py
psychedelic.egg-info/PKG-INFO
psychedelic.egg-info/SOURCES.txt
psychedelic.egg-info/dependency_links.txt
psychedelic.egg-info/not-zip-safe
psychedelic.egg-info/requires.txt
psychedelic.egg-info/top_level.txt