Metadata-Version: 1.0
Name: psychedelic
Version: 2020.2.15.2122
Summary: utilities for machine learning etc.
Home-page: https://github.com/wdbm/psychedelic
Author: Will Breaden Madden
Author-email: wbm@protonmail.ch
License: GPLv3
Platform: UNKNOWN
